velocity_modelling/__init__.py
velocity_modelling/basin_model.py
velocity_modelling/bounding_box.py
velocity_modelling/constants.py
velocity_modelling/data_helper.py
velocity_modelling/data_root.py
velocity_modelling/geometry.py
velocity_modelling/global_model.py
velocity_modelling/gtl.py
velocity_modelling/interpolate.py
velocity_modelling/nzcvm_sample.cfg
velocity_modelling/registry.py
velocity_modelling/threshold.py
velocity_modelling/velocity1d.py
velocity_modelling/velocity3d.py
velocity_modelling/model_versions/2p02.yaml
velocity_modelling/model_versions/2p03.yaml
velocity_modelling/model_versions/2p06.yaml
velocity_modelling/model_versions/2p07.yaml
velocity_modelling/model_versions/2p08.yaml
velocity_modelling/model_versions/2p09.yaml
velocity_modelling/model_versions/2p09_no_basin.yaml
velocity_modelling/scripts/__init__.py
velocity_modelling/scripts/extract_cross_section.py
velocity_modelling/scripts/generate_1d_profiles.py
velocity_modelling/scripts/generate_3d_model.py
velocity_modelling/scripts/generate_thresholds.py
velocity_modelling/submodel/__init__.py
velocity_modelling/submodel/bpv_submod_v1.py
velocity_modelling/submodel/bpv_submod_v2.py
velocity_modelling/submodel/bpv_submod_v3.py
velocity_modelling/submodel/bpv_submod_v4.py
velocity_modelling/submodel/canterbury1d_submod.py
velocity_modelling/submodel/ep_tomography_submod_v2010.py
velocity_modelling/submodel/miocene_submod_v1.py
velocity_modelling/submodel/miocene_submod_v2.py
velocity_modelling/submodel/nan_submod.py
velocity_modelling/submodel/paleogene_submod_v1.py
velocity_modelling/submodel/paleogene_submod_v2.py
velocity_modelling/submodel/pliocene_submod_v1.py
velocity_modelling/submodel/pliocene_submod_v2.py
velocity_modelling/submodel/pn_pliocene_submod_v1.py
velocity_modelling/tools/__init__.py
velocity_modelling/tools/compare_emod3d.py
velocity_modelling/tools/compare_hdf5.py
velocity_modelling/tools/convert_hdf5_to_emod3d.py
velocity_modelling/write/__init__.py
velocity_modelling-2025.12.1.dist-info/METADATA
velocity_modelling-2025.12.1.dist-info/WHEEL
velocity_modelling-2025.12.1.dist-info/entry_points.txt
velocity_modelling-2025.12.1.dist-info/top_level.txt
velocity_modelling-2025.12.1.dist-info/RECORD
