Metadata-Version: 2.4
Name: velocity_modelling
Version: 2025.12.1
Summary: Velocity modelling library
Author: ucgmsim
Requires-Python: <3.14,>=3.11
Requires-Dist: numpy
Requires-Dist: h5py
Requires-Dist: pandas[parquet]
Requires-Dist: matplotlib
Requires-Dist: shapely
Requires-Dist: geopandas
Requires-Dist: numba
Requires-Dist: pyyaml
Requires-Dist: tqdm
Requires-Dist: typer
Requires-Dist: threadpoolctl
Requires-Dist: cartopy
Requires-Dist: qcore-utils
Provides-Extra: test
Requires-Dist: hypothesis[numpy]; extra == "test"
Requires-Dist: pytest; extra == "test"
Requires-Dist: pytest-cov; extra == "test"
Requires-Dist: pytest-repeat; extra == "test"
